LICENSE
MANIFEST.in
README.md
pyproject.toml
requirements.txt
setup.py
bin/fchart3
bin/fchart3-atlas
fchart3/__init__.py
fchart3/base_types.py
fchart3/config_loader.py
fchart3/configuration.py
fchart3/constellation.py
fchart3/deepsky_catalog.py
fchart3/deepsky_object.py
fchart3/geodesic_binfile_reader.py
fchart3/geodesic_grid.py
fchart3/geodesic_star_catalog_gaia.py
fchart3/highlights.py
fchart3/hnsky_deepsky.py
fchart3/horizon_landscape.py
fchart3/htm_grid.py
fchart3/label_potential.py
fchart3/milkyway.py
fchart3/outlines_deepsky.py
fchart3/pgc_deepsky.py
fchart3/skymap_engine.py
fchart3/solar_system_body.py
fchart3/used_catalogs.py
fchart3/vector_math.py
fchart3/vic.py
fchart3/viewport_transformer.py
fchart3.egg-info/PKG-INFO
fchart3.egg-info/SOURCES.txt
fchart3.egg-info/dependency_links.txt
fchart3.egg-info/requires.txt
fchart3.egg-info/top_level.txt
fchart3/astro/__init__.py
fchart3/astro/astrocalc.py
fchart3/astro/np_astrocalc.py
fchart3/astro/precession.py
fchart3/cli/__init__.py
fchart3/cli/search_object_utils.py
fchart3/cli/solar_system.py
fchart3/data/default.conf
fchart3/data/label_positions.txt
fchart3/data/catalogs/PGC.dat
fchart3/data/catalogs/PGC_update.dat
fchart3/data/catalogs/bsc5.dat
fchart3/data/catalogs/constbndJ2000.dat
fchart3/data/catalogs/constellation_boundaries.dat
fchart3/data/catalogs/constellationship_western.fab
fchart3/data/catalogs/convert_stellarium_boundaries.txt
fchart3/data/catalogs/cross-id.dat
fchart3/data/catalogs/deep_sky.hnd
fchart3/data/catalogs/milkyway.dat
fchart3/data/catalogs/milkyway_enhanced_10k.dat
fchart3/data/catalogs/milkyway_enhanced_30k.dat
fchart3/data/catalogs/namedstars.dat
fchart3/data/catalogs/outlines_catgen.dat
fchart3/data/catalogs/starnames.dat
fchart3/data/catalogs/stars_0_0v0_14.cat
fchart3/data/catalogs/stars_1_0v0_14.cat
fchart3/data/catalogs/stars_2_0v0_14.cat
fchart3/data/catalogs/stars_3_0v0_9.cat
fchart3/data/catalogs/unnamedstars.dat
fchart3/data/catalogs/vic.txt
fchart3/graphics/__init__.py
fchart3/graphics/graphics_cairo.py
fchart3/graphics/graphics_interface.py
fchart3/graphics/graphics_skia.py
fchart3/graphics/graphics_tikz.py
