Metadata-Version: 2.4
Name: fchart3
Version: 0.12.2
Summary: Collection of Python scripts to make beautiful deepsky charts in various formats
Home-page: https://github.com/skybber/fchart3
Author: Vladimir Dvorak<lada.dvorak7@gmail.com
Author-email: "Vladimir Dvorak (skybber)" <lada.dvorak7@gmail.com>
Project-URL: Homepage, https://github.com/skybber/fchart3
Project-URL: Bug Tracker, https://github.com/skybber/fchart3/issues
Keywords: fchart3 starchart star charts finder chart astronomy map
Classifier: Programming Language :: Python :: 3
Classifier: License :: OSI Approved :: GNU General Public License v2 (GPLv2)
Classifier: Operating System :: OS Independent
Requires-Python: >=3.0
License-File: LICENSE
Requires-Dist: numpy
Requires-Dist: pycairo
Requires-Dist: Pillow
Requires-Dist: skia-python
Requires-Dist: pandas
Requires-Dist: skyfield
Dynamic: author
Dynamic: home-page
Dynamic: license-file
